       0: lconst_0
       1: l2f
       2: iconst_5
       3: pop
       4: iconst_4
       5: nop
       6: fconst_2
       7: iconst_3
       8: istore_3
       9: f2d
      10: sipush        -6641
      13: iconst_5
      14: istore_2
      15: sipush        -4067
      18: ixor
      19: aload_0
      20: fconst_1
      21: dup_x2
      22: iconst_m1
      23: nop
      24: pop2
      25: iconst_1
      26: swap
      27: dup2
      28: dconst_1
      29: iload_2
      30: i2l
      31: l2d
      32: aload_0
      33: sipush        -4916
      36: aaload
      37: lconst_0
      38: lstore_1
      39: bipush        106
      41: fconst_2
      42: dup
      43: fstore_2
      44: dup2
      45: lconst_1
      46: fconst_0
      47: iload_3
      48: istore_2
      49: pop
      50: iconst_m1
      51: lshr
      52: lstore        207
      54: dup_x2
      55: iconst_4
      56: i2l
      57: fconst_1
      58: dup
      59: fstore        239
      61: aload_0
      62: aload_0
      63: astore_1
      64: dconst_1
      65: d2f
      66: aconst_null
      67: astore        180
      69: lconst_0
      70: fconst_2
      71: iconst_2
      72: bipush        -99
      74: istore        80
      76: aconst_null
      77: astore        149
      79: i2f
      80: nop
      81: iconst_0
      82: istore_0
      83: fcmpg
      84: iload_3
      85: dup2
      86: dup2
      87: pop2
      88: dup2
      89: sipush        22171
      92: istore_0
      93: fconst_0
      94: dconst_0
      95: dup2_x1
      96: dstore        107
      98: iconst_0
      99: dconst_0
     100: lconst_1
     101: iconst_4
     102: iload_0
     103: iload_3
     104: istore_0
     105: i2s
     106: nop
     107: ixor
     108: iconst_3
     109: ior
     110: fconst_1
     111: nop
     112: fconst_1
     113: dup_x1
     114: iconst_2
     115: aload         149
     117: astore_2
     118: i2s
     119: istore_1
     120: fsub
     121: swap
     122: fstore_2
     123: fstore_1
     124: iconst_m1
     125: istore_0
     126: i2c
     127: i2s
     128: i2c
     129: istore        87
     131: dup2
     132: land
     133: iconst_3
     134: iconst_4
     135: ineg
     136: lconst_1
     137: iconst_5
     138: i2s
     139: iconst_m1
     140: ldc           #7                  // class test
     142: dup
     143: fconst_1
     144: dup_x1
     145: iconst_0
     146: bipush        91
     148: i2b
     149: iushr
     150: i2d
     151: iconst_5
     152: fload_2
     153: fconst_2
     154: dup
     155: dconst_0
     156: iconst_5
     157: i2s
     158: pop
     159: dneg
     160: iconst_5
     161: dup_x2
     162: istore_0
     163: dup2_x2
     164: sipush        -25964
     167: i2c
     168: istore_3
     169: dconst_1
     170: dup2
     171: dup2_x2
     172: dup2_x2
     173: d2f
     174: sipush        -16190
     177: iconst_0
     178: dconst_0
     179: d2f
     180: dup_x1
     181: dup
     182: fsub
     183: fload_1
     184: f2d
     185: aconst_null
     186: monitorenter
     187: dstore_0
     188: dup_x2
     189: dload_0
     190: fconst_0
     191: iload_3
     192: aconst_null
     193: dup2_x1
     194: dup2_x1
     195: swap
     196: newarray       byte
     198: dload_0
     199: fload_2
     200: fconst_1
     201: iconst_5
     202: ineg
     203: iconst_2
     204: ineg
     205: iand
     206: dconst_0
     207: iconst_1
     208: fconst_0
     209: fstore_0
     210: dconst_0
     211: fconst_1
     212: fstore_1
     213: fload         0
     215: fneg
     216: iconst_2
     217: ineg
     218: pop
     219: fstore_3
     220: d2i
     221: iushr
     222: lconst_1
     223: bipush        -54
     225: lconst_0
     226: fload_2
     227: lconst_0
     228: fload_1
     229: iconst_2
     230: dup2
     231: dconst_0
     232: iconst_0
     233: lconst_0
     234: iconst_m1
     235: istore_1
     236: fconst_1
     237: fconst_1
     238: fmul
     239: fload_2
     240: fdiv
     241: iconst_3
     242: iconst_2
     243: isub
     244: i2c
     245: iconst_3
     246: dconst_1
     247: dconst_1
     248: ddiv
     249: iconst_4
     250: iconst_3
     251: iconst_3
     252: i2c
     253: pop2
     254: iconst_1
     255: fconst_1
     256: dconst_1
     257: lconst_1
     258: lstore_1
     259: iconst_3
     260: sipush        18350
     263: i2b
     264: fconst_1
     265: lconst_1
     266: fload_3
     267: f2l
     268: lstore_0
     269: lload_0
     270: lcmp
     271: swap
     272: aconst_null
     273: iconst_m1
     274: aconst_null
     275: astore_3
     276: iconst_3
     277: isub
     278: saload
     279: lload_0
     280: bipush        54
     282: iconst_5
     283: ishl
     284: istore_1
     285: lstore_2
     286: iconst_2
     287: istore        134
     289: dconst_0
     290: fconst_1
     291: lload_2
     292: fconst_1
     293: fstore_2
     294: dup2
     295: lconst_0
     296: fload_2
     297: iconst_m1
     298: iconst_3
     299: i2c
     300: lconst_1
     301: l2i
     302: i2s
     303: iload_1
     304: iconst_0
     305: idiv
     306: fload         2
     308: iconst_m1
     309: bipush        121
     311: iconst_4
     312: dup2_x2
     313: dup_x1
     314: iushr
     315: iand
     316: fconst_1
     317: iconst_2
     318: iconst_0
     319: pop2
     320: lconst_1
     321: iconst_3
     322: iconst_1
     323: pop
     324: iconst_2
     325: iconst_0
     326: idiv
     327: fconst_0
     328: iload_1
     329: dconst_0
     330: fload_2
     331: iconst_3
     332: i2s
     333: dup
     334: bipush        106
     336: isub
     337: dup2_x1
     338: i2s
     339: i2f
     340: fneg
     341: dup
     342: iconst_5
     343: istore_2
     344: fconst_1
     345: fcmpl
     346: iconst_1
     347: dload         107
     349: dup2_x1
     350: dstore_3
     351: dup_x2
     352: lconst_1
     353: pop2
     354: istore_1
     355: dup2_x1
     356: nop
     357: fconst_1
     358: dup
     359: bipush        21
     361: iload_1
     362: isub
     363: istore        207
     365: dup2
     366: fsub
     367: iload_1
     368: i2b
     369: bipush        102
     371: iconst_5
     372: isub
     373: ishr
     374: dup_x1
     375: dconst_1
     376: fconst_0
     377: iconst_m1
     378: iconst_0
     379: swap
     380: iconst_0
     381: pop2
     382: istore_0
     383: iconst_4
     384: dup
     385: ior
     386: ineg
     387: iload_0
     388: ior
     389: i2s
     390: aload         180
     392: iload_0
     393: iconst_1
     394: ineg
     395: iload_0
     396: i2s
     397: i2f
     398: fconst_0
     399: iconst_m1
     400: i2b
     401: dconst_0
     402: dstore_1
     403: i2f
     404: sipush        5362
     407: i2l
     408: lstore_0
     409: fcmpg
     410: iconst_4
     411: sipush        -11956
     414: lconst_1
     415: ldc           #7                  // class test
     417: pop
     418: dload_3
     419: iconst_4
     420: iconst_m1
     421: fconst_1
     422: fconst_2
     423: frem
     424: iconst_m1
     425: dload_3
     426: fconst_2
     427: iconst_m1
     428: i2l
     429: dup2_x1
     430: iconst_5
     431: dconst_0
     432: dconst_1
     433: dcmpg
     434: fconst_0
     435: fneg
     436: dconst_1
     437: iconst_3
     438: dup
     439: istore_0
     440: istore_3
     441: d2f
     442: fadd
     443: iconst_3
     444: ineg
     445: dup2
     446: i2b
     447: iconst_5
     448: swap
     449: iconst_1
     450: isub
     451: istore_0
     452: lconst_1
     453: iconst_m1
     454: iconst_5
     455: istore_0
     456: lshr
     457: dconst_1
     458: dup2_x2
     459: iinc          80, 46
     462: iload_3
     463: iconst_4
     464: istore_0
     465: istore_1
     466: sipush        19341
     469: istore_0
     470: dup2
     471: aconst_null
     472: lconst_1
     473: iload_1
     474: sipush        29217
     477: ishl
     478: fconst_2
     479: fstore_0
     480: istore_0
     481: nop
     482: pop2
     483: arraylength
     484: sipush        -18573
     487: istore_2
     488: iconst_3
     489: iconst_0
     490: i2d
     491: dneg
     492: bipush        123
     494: pop
     495: iconst_3
     496: dup
     497: dconst_0
     498: iconst_1
     499: dup_x2
     500: iload_0
     501: pop
     502: istore_3
     503: dstore        203
     505: isub
     506: iload_3
     507: pop2
     508: i2d
     509: fconst_2
     510: fstore_3
     511: ddiv
     512: iconst_0
     513: ldc           #7                  // class test
     515: astore        18
     517: istore_2
     518: fconst_1
     519: iconst_3
     520: ldc           #2                  // class java/lang/Object
     522: aconst_null
     523: dup2_x1
     524: iload_2
     525: i2d
     526: iconst_3
     527: iconst_5
     528: i2l
     529: pop2
     530: fconst_1
     531: iconst_m1
     532: aconst_null
     533: lconst_0
     534: lneg
     535: lstore_1
     536: fload         3
     538: fstore        80
     540: astore_1
     541: fconst_2
     542: lconst_0
     543: iconst_4
     544: i2c
     545: iconst_2
     546: istore_3
     547: i2d
     548: dneg
     549: iload_3
     550: iconst_1
     551: iconst_1
     552: sipush        14841
     555: nop
     556: iload_3
     557: iconst_0
     558: fconst_2
     559: dup
     560: bipush        73
     562: iconst_0
     563: dup_x1
     564: iconst_5
     565: iload_0
     566: iadd
     567: swap
     568: aconst_null
     569: iconst_1
     570: fconst_1
     571: aload_1
     572: dup
     573: iconst_0
     574: dup
     575: istore_3
     576: dload         107
     578: iload_0
     579: i2l
     580: aload_1
     581: astore_0
     582: fload         80
     584: aload_1
     585: iconst_4
     586: fconst_2
     587: fstore_1
     588: iconst_1
     589: fload         239
     591: fstore_1
     592: pop2
     593: aload_0
     594: iconst_m1
     595: iconst_3
     596: sipush        -2404
     599: i2f
     600: dup_x2
     601: fstore_1
     602: ishl
     603: fload_1
     604: f2d
     605: dconst_1
     606: d2i
     607: lconst_0
     608: iconst_1
     609: ineg
     610: fconst_0
     611: iload_3
     612: iconst_m1
     613: imul
     614: pop
     615: iconst_5
     616: sipush        15247
     619: iconst_5
     620: irem
     621: iushr
     622: dup_x1
     623: i2s
     624: dup2_x2
     625: iconst_5
     626: dconst_0
     627: iconst_1
     628: i2f
     629: dup
     630: f2i
     631: dconst_0
     632: aload_0
     633: iconst_1
     634: aload_0
     635: lconst_0
     636: pop2
     637: iconst_1
     638: daload
     639: lconst_1
     640: aload_0
     641: bipush        97
     643: istore        243
     645: iconst_4
     646: dload         107
     648: aconst_null
     649: iconst_2
     650: dup
     651: i2f
     652: fconst_1
     653: iconst_0
     654: iconst_m1
     655: fconst_2
     656: iconst_4
     657: nop
     658: dup_x2
     659: i2f
     660: fstore_2
     661: dup
     662: iconst_5
     663: iload_3
     664: dup
     665: istore_3
     666: i2d
     667: aload_0
     668: fload_1
     669: dup_x1
     670: pop2
     671: lconst_0
     672: iconst_0
     673: dconst_0
     674: sipush        -7292
     677: nop
     678: iconst_2
     679: iload_3
     680: iconst_4
     681: dup_x2
     682: pop
     683: dup
     684: imul
     685: iconst_3
     686: ishl
     687: irem
     688: istore_2
     689: newarray       int
     691: fconst_0
     692: dup
     693: sipush        -15092
     696: dup2_x1
     697: i2l
     698: iconst_1
     699: fconst_2
     700: dup
     701: frem
     702: dconst_1
     703: dneg
     704: iconst_2
     705: i2b
     706: iconst_3
     707: newarray       short
     709: ldc           #2                  // class java/lang/Object
     711: bipush        5
     713: dup2_x2
     714: bipush        118
     716: iconst_0
     717: istore_1
     718: dup
     719: dconst_1
     720: iconst_1
     721: iload_2
     722: iload_3
     723: iadd
     724: aconst_null
     725: iload_1
     726: baload
     727: dup2
     728: lconst_0
     729: fconst_1
     730: fconst_0
     731: fstore_3
     732: fstore_2
     733: iconst_m1
     734: i2c
     735: pop
     736: dconst_0
     737: aload_0
     738: dconst_1
     739: bipush        -103
     741: fconst_2
     742: dup2_x2
     743: fload_2
     744: fadd
     745: iconst_2
     746: i2c
     747: pop
     748: pop2
     749: dstore_2
     750: fconst_1
     751: frem
     752: pop2
     753: astore        250
     755: iconst_4
     756: i2l
     757: lconst_0
     758: aload         250
     760: dup
     761: sipush        -31801
     764: iconst_5
     765: lconst_0
     766: l2f
     767: f2l
     768: dconst_0
     769: aload_0
     770: iload_1
     771: iconst_2
     772: i2d
     773: pop2
     774: aconst_null
     775: astore_1
     776: istore_0
     777: iload_0
     778: iconst_3
     779: newarray       double
     781: astore_0
     782: daload
     783: iconst_4
     784: aload         250
     786: dconst_1
     787: iconst_4
     788: istore        74
     790: dload_2
     791: dmul
     792: dstore_3
     793: lconst_0
     794: iconst_3
     795: i2b
     796: iconst_4
     797: iadd
     798: iconst_3
     799: iand
     800: iconst_2
     801: fconst_1
     802: iconst_2
     803: iconst_3
     804: aload_0
     805: dconst_1
     806: fconst_2
     807: lconst_1
     808: iconst_0
     809: fconst_2
     810: fconst_1
     811: fcmpg
     812: iconst_4
     813: aload_0
     814: sipush        -20461
     817: istore_1
     818: iconst_0
     819: i2c
     820: dconst_1
     821: aconst_null
     822: fconst_2
     823: iconst_m1
     824: dup2
     825: dup
     826: nop
     827: istore        60
     829: aload_0
     830: iconst_3
     831: ldc           #7                  // class test
     833: pop
     834: iconst_2
     835: dup2_x1
     836: dup2
     837: istore_0
     838: aconst_null
     839: swap
     840: istore_1
     841: lconst_1
     842: bipush        94
     844: dup_x2
     845: dconst_1
     846: d2l
     847: iconst_1
     848: lconst_1
     849: lstore_0
     850: lshr
     851: iload         134
     853: fconst_0
     854: dup2
     855: fstore_0
     856: ineg
     857: iload         87
     859: iushr
     860: newarray       int
     862: dup2_x1
     863: dup
     864: aconst_null
     865: fconst_2
     866: dconst_0
     867: fconst_1
     868: fstore        117
     870: dstore_0
     871: pop2
     872: dup2
     873: iconst_3
     874: iconst_5
     875: i2c
     876: i2d
     877: dstore_0
     878: sipush        30839
     881: dload_3
     882: ldc           #2                  // class java/lang/Object
     884: iload         134
     886: fconst_0
     887: fconst_0
     888: fmul
     889: fstore_0
     890: nop
     891: istore_1
     892: iconst_m1
     893: bipush        83
     895: dup_x2
     896: iand
     897: ineg
     898: ineg
     899: istore_2
     900: iconst_1
     901: bipush        3
     903: dconst_0
     904: lconst_1
     905: iconst_3
     906: sipush        -26293
     909: pop2
     910: fconst_0
     911: fconst_1
     912: fconst_2
     913: lconst_1
     914: dup2
     915: iconst_1
     916: istore_1
     917: fconst_1
     918: fstore_2
     919: lrem
     920: dload_3
     921: fconst_1
     922: aconst_null
     923: astore_0
     924: f2l
     925: nop
     926: fload_2
     927: fstore        39
     929: fconst_2
     930: ldc           #7                  // class test
     932: dload_3
     933: d2i
     934: i2b
     935: iconst_1
     936: irem
     937: i2c
     938: i2l
     939: fconst_2
     940: dconst_0
     941: d2l
     942: nop
     943: dconst_0
     944: iconst_0
     945: fconst_0
     946: f2i
     947: aconst_null
     948: iload_1
     949: istore_0
     950: iload_1
     951: iload_0
     952: sipush        -25773
     955: i2s
     956: pop
     957: lconst_1
     958: iload_1
     959: aload         18
     961: monitorexit
     962: i2d
     963: iconst_1
     964: iconst_5
     965: i2s
     966: i2d
     967: lconst_1
     968: lstore_3
     969: dstore_2
     970: istore_2
     971: iconst_2
     972: i2b
     973: iload_1
     974: irem
     975: aload         180
     977: dup
     978: astore        165
     980: iconst_4
     981: iload_2
     982: iconst_m1
     983: istore_2
     984: isub
     985: dconst_0
     986: dup2_x1
     987: dstore_1
     988: i2l
     989: dconst_0
     990: bipush        53
     992: iconst_1
     993: iconst_3
     994: ishl
     995: iushr
     996: istore_2
     997: fconst_1
     998: fconst_1
     999: dup2_x2
    1000: dup2_x2
    1001: dup
    1002: fconst_0
    1003: fsub
    1004: dload         203
    1006: dstore_1
    1007: dup
    1008: dconst_0
    1009: dload         107
    1011: lconst_1
    1012: aconst_null
    1013: sipush        14230
    1016: caload
    1017: i2c
    1018: aconst_null
    1019: dload_1
    1020: iconst_0
    1021: dconst_0
    1022: d2l
    1023: iconst_4
    1024: lconst_1
    1025: fconst_0
    1026: aload         18
    1028: iconst_2
    1029: pop2
    1030: iconst_5
    1031: iconst_5
    1032: dload_1
    1033: dneg
    1034: sipush        22194
    1037: iconst_5
    1038: dup2
    1039: nop
    1040: fconst_2
    1041: fstore        19
    1043: i2s
    1044: fconst_1
    1045: bipush        83
    1047: newarray       byte
    1049: lconst_1
    1050: lstore_2
    1051: sipush        17720
    1054: sipush        -20292
    1057: istore_1
    1058: istore_1
    1059: pop2
    1060: fconst_2
    1061: fconst_2
    1062: iconst_m1
    1063: nop
    1064: dup2
    1065: dconst_0
    1066: dstore_1
    1067: i2s
    1068: i2d
    1069: dload         107
    1071: lconst_0
    1072: pop2
    1073: iconst_0
    1074: nop
    1075: iload         87
    1077: dconst_0
    1078: fconst_1
    1079: lconst_0
    1080: iconst_0
    1081: dup
    1082: bipush        -79
    1084: iconst_m1
    1085: iload         74
    1087: dup2
    1088: dconst_1
    1089: iconst_1
    1090: i2s
    1091: iconst_2
    1092: aload         165
    1094: astore_1
    1095: dup2_x2
    1096: fconst_1
    1097: dconst_0
    1098: dstore_0
    1099: fneg
    1100: iconst_0
    1101: iconst_5
    1102: sipush        -29428
    1105: istore_1
    1106: iload_1
    1107: i2d
    1108: dstore_3
    1109: dconst_1
    1110: iconst_m1
    1111: dconst_0
    1112: lconst_0
    1113: nop
    1114: bipush        -51
    1116: istore_3
    1117: iconst_0
    1118: sipush        -3374
    1121: iconst_1
    1122: iconst_m1
    1123: fconst_2
    1124: iconst_1
    1125: istore        14
    1127: iconst_3
    1128: newarray       float
    1130: aload         18
    1132: pop
    1133: monitorexit
    1134: dup2
    1135: iconst_1
    1136: iconst_m1
    1137: iload_3
    1138: i2d
    1139: iconst_4
    1140: istore_3
    1141: dup2_x2
    1142: bipush        -23
    1144: fconst_1
    1145: iconst_1
    1146: fload         19
    1148: dup2_x1
    1149: fload         239
    1151: fstore_1
    1152: iconst_0
    1153: dup2_x1
    1154: lconst_1
    1155: iconst_3
    1156: dup_x2
    1157: istore_3
    1158: iload_3
    1159: lshr
    1160: iconst_1
    1161: dconst_1
    1162: pop2
    1163: sipush        17469
    1166: aconst_null
    1167: lconst_0
    1168: dup2_x1
    1169: iconst_m1
    1170: istore_0
    1171: fconst_0
    1172: dup_x2
    1173: iconst_0
    1174: iload_0
    1175: iushr
    1176: i2c
    1177: fconst_0
    1178: dconst_1
    1179: iconst_4
    1180: iconst_0
    1181: iconst_1
    1182: i2d
    1183: d2f
    1184: sipush        -11483
    1187: istore_3
    1188: lconst_1
    1189: fload_1
    1190: dup
    1191: dup_x1
    1192: fstore        111
    1194: pop
    1195: nop
    1196: fstore_2
    1197: l2d
    1198: dneg
    1199: fload_2
    1200: aconst_null
    1201: astore_2
    1202: aload         180
    1204: astore_0
    1205: fstore        231
    1207: iconst_1
    1208: bipush        103
    1210: iconst_2
    1211: iconst_1
    1212: ineg
    1213: aload_0
    1214: dconst_1
    1215: dup2
    1216: return
